{
  "room": [
    {
      "id": 1,
      "room_name": "R001",
      "price": 1000000,
      "description": "Kamar Bagus dan Nyaman",
      "url_video": "https://www.youtube.com/shorts/UeyYJkoZ5u8"
    },
    {
      "id": 2,
      "room_name": "R002",
      "price": 1100000,
      "description": "Kamar Bagus dan Lucu",
      "url_video": "https://www.youtube.com/shorts/JvU3dY4-fBQ"
    },
    {
      "id": 3,
      "room_name": "R003",
      "price": 1200000,
      "description": "Kamar Apik dan Lucu",
      "url_video": "https://youtube.com/shorts/VRVrTvM6EBI?si=QnkBcKsjb-E1oCBm"
    }
  ]
}
